pysmd/__init__.py
pysmd/example.py
pysmd-0.1.dist-info/LICENSE
pysmd-0.1.dist-info/METADATA
pysmd-0.1.dist-info/WHEEL
pysmd-0.1.dist-info/top_level.txt
pysmd-0.1.dist-info/RECORD
